azure/appconfiguration/provider/__init__.py
azure/appconfiguration/provider/_azureappconfigurationprovider.py
azure/appconfiguration/provider/_azureappconfigurationproviderbase.py
azure/appconfiguration/provider/_client_manager.py
azure/appconfiguration/provider/_client_manager_base.py
azure/appconfiguration/provider/_constants.py
azure/appconfiguration/provider/_discovery.py
azure/appconfiguration/provider/_json.py
azure/appconfiguration/provider/_models.py
azure/appconfiguration/provider/_refresh_timer.py
azure/appconfiguration/provider/_request_tracing_context.py
azure/appconfiguration/provider/_user_agent.py
azure/appconfiguration/provider/_version.py
azure/appconfiguration/provider/py.typed
azure/appconfiguration/provider/_key_vault/__init__.py
azure/appconfiguration/provider/_key_vault/_secret_provider.py
azure/appconfiguration/provider/_key_vault/_secret_provider_base.py
azure/appconfiguration/provider/aio/__init__.py
azure/appconfiguration/provider/aio/_async_client_manager.py
azure/appconfiguration/provider/aio/_async_discovery.py
azure/appconfiguration/provider/aio/_azureappconfigurationproviderasync.py
azure/appconfiguration/provider/aio/_key_vault/__init__.py
azure/appconfiguration/provider/aio/_key_vault/_async_secret_provider.py
azure_appconfiguration_provider-2.3.1.dist-info/licenses/LICENSE
azure_appconfiguration_provider-2.3.1.dist-info/METADATA
azure_appconfiguration_provider-2.3.1.dist-info/WHEEL
azure_appconfiguration_provider-2.3.1.dist-info/top_level.txt
azure_appconfiguration_provider-2.3.1.dist-info/RECORD
