Metadata-Version: 2.4
Name: azure-appconfiguration-provider
Version: 2.3.1
Summary: Microsoft App Configuration Provider Library for Python
Home-page: https://github.com/Azure/azure-sdk-for-python/tree/main/sdk/appconfiguration/azure-appconfiguration-provider
Author: Microsoft Corporation
Author-email: azpysdkhelp@microsoft.com
License: MIT License
Keywords: azure,azure sdk
Classifier: Development Status :: 5 - Production/Stable
Classifier: Programming Language :: Python
Classifier: Programming Language :: Python :: 3 :: Only
Classifier: Programming Language :: Python :: 3
Classifier: Programming Language :: Python :: 3.7
Classifier: Programming Language :: Python :: 3.8
Classifier: Programming Language :: Python :: 3.9
Classifier: Programming Language :: Python :: 3.10
Classifier: Programming Language :: Python :: 3.11
Classifier: License :: OSI Approved :: MIT License
Requires-Python: >=3.6
License-File: LICENSE
Requires-Dist: azure-core>=1.30.0
Requires-Dist: azure-appconfiguration>=1.6.1
Requires-Dist: azure-keyvault-secrets>=4.3.0
Requires-Dist: dnspython>=2.6.1
Dynamic: author
Dynamic: author-email
Dynamic: classifier
Dynamic: description
Dynamic: description-content-type
Dynamic: home-page
Dynamic: keywords
Dynamic: license
Dynamic: license-file
Dynamic: requires-dist
Dynamic: requires-python
Dynamic: summary
